db/__init__.py
db/py.typed
m4rkw_db-0.0.9.dist-info/METADATA
m4rkw_db-0.0.9.dist-info/WHEEL
m4rkw_db-0.0.9.dist-info/top_level.txt
m4rkw_db-0.0.9.dist-info/RECORD
