Metadata-Version: 2.4
Name: m4rkw-db
Version: 0.0.9
Summary: db
Author-email: Your Name <your@email.com>
Requires-Dist: pymysql
